bteval/__about__.py
bteval/__init__.py
bteval/metrics.py
bteval-0.2.0.dist-info/METADATA
bteval-0.2.0.dist-info/WHEEL
bteval-0.2.0.dist-info/licenses/LICENSE
bteval-0.2.0.dist-info/RECORD
