Metadata-Version: 2.1
Name: bteval
Version: 0.2.0
Summary: BTEval is a Python library for measuring the robustness of natural language understanding models to speech recognition errors.
Project-URL: Documentation, https://github.com/marekkubis/bteval#readme
Project-URL: Homepage, https://github.com/marekkubis/bteval
Project-URL: Issues, https://github.com/marekkubis/bteval/issues
Project-URL: Source, https://github.com/marekkubis/bteval
Author-email: Marek Kubis <marek.kubis@gmail.com>
License-Expression: MIT
License-File: LICENSE
Keywords: asr,backtranscription,nlu,tts
Classifier: Development Status :: 4 - Beta
Classifier: Programming Language :: Python
Classifier: Programming Language :: Python :: 3.10
Classifier: Programming Language :: Python :: 3.11
Classifier: Programming Language :: Python :: 3.12
Classifier: Programming Language :: Python :: Implementation :: CPython
Classifier: Programming Language :: Python :: Implementation :: PyPy
Classifier: Topic :: Scientific/Engineering :: Artificial Intelligence
Requires-Python: >=3.10
